cmip_ref_celery/__init__.py
cmip_ref_celery/app.py
cmip_ref_celery/cli.py
cmip_ref_celery/executor.py
cmip_ref_celery/py.typed
cmip_ref_celery/tasks.py
cmip_ref_celery/worker_tasks.py
cmip_ref_celery/celeryconf/__init__.py
cmip_ref_celery/celeryconf/base.py
cmip_ref_celery/celeryconf/dev.py
cmip_ref_celery/celeryconf/prod.py
cmip_ref_celery-0.4.1.dist-info/METADATA
cmip_ref_celery-0.4.1.dist-info/WHEEL
cmip_ref_celery-0.4.1.dist-info/entry_points.txt
cmip_ref_celery-0.4.1.dist-info/licenses/LICENCE
cmip_ref_celery-0.4.1.dist-info/licenses/NOTICE
cmip_ref_celery-0.4.1.dist-info/RECORD
