Metadata-Version: 2.4
Name: cmip_ref_celery
Version: 0.4.1
Summary: Celery app for mananging tasks and workers
Author-email: Jared Lewis <jared.lewis@climate-resource.com>
License-File: LICENCE
License-File: NOTICE
Classifier: Development Status :: 4 - Beta
Classifier: Intended Audience :: Developers
Classifier: Intended Audience :: Science/Research
Classifier: Operating System :: OS Independent
Classifier: Programming Language :: Python
Classifier: Programming Language :: Python :: 3
Classifier: Programming Language :: Python :: 3.11
Classifier: Programming Language :: Python :: 3.12
Classifier: Programming Language :: Python :: 3.13
Classifier: Topic :: Scientific/Engineering
Requires-Python: >=3.11
Requires-Dist: celery[redis]>=5.4.0
Requires-Dist: cmip-ref-core
Requires-Dist: environs>=9
Requires-Dist: loguru>=0.7.2
Requires-Dist: tqdm>=4.67.1
Requires-Dist: typer>=0.12.0
